atcom/__init__.py
atcom/__version__.py
atcom/cli.py
atcom/modems.py
atcom/utils.py
atcom-0.2.0.dist-info/LICENSE
atcom-0.2.0.dist-info/METADATA
atcom-0.2.0.dist-info/WHEEL
atcom-0.2.0.dist-info/entry_points.txt
atcom-0.2.0.dist-info/top_level.txt
atcom-0.2.0.dist-info/RECORD
