Metadata-Version: 2.1
Name: atcom
Version: 0.2.0
Summary: A tool which makes AT communication easier.
Home-page: https://github.com/sixfab/atcom
Author: Bugra Isguzar
Author-email: bugra@sixfab.com
License: MIT
Platform: UNKNOWN
Classifier: License :: OSI Approved :: MIT License
Classifier: Programming Language :: Python
Classifier: Programming Language :: Python :: 3
Classifier: Programming Language :: Python :: 3.6
Classifier: Programming Language :: Python :: Implementation :: CPython
Classifier: Programming Language :: Python :: Implementation :: PyPy
Requires-Python: >=3.6.0
Requires-Dist: click
Requires-Dist: pyserial
Requires-Dist: pyyaml
